arcgitflow/gitflow.py
arcgitflow-0.5.5.dist-info/LICENSE
arcgitflow-0.5.5.dist-info/LICENSE.txt
arcgitflow-0.5.5.dist-info/METADATA
arcgitflow-0.5.5.dist-info/WHEEL
arcgitflow-0.5.5.dist-info/entry_points.txt
arcgitflow-0.5.5.dist-info/top_level.txt
arcgitflow-0.5.5.dist-info/RECORD
